{
  "title": "Consultation",
  "content": [
    {
      "title": "p1",
      "textcontent": "Mes conseils sont axés sur les objectifs, les solutions et les ressources. Elle se fonde sur ce qui est faisable et en même temps essaie soigneusement d'inclure ce qui est souhaitable.\n\nLa pensée en réseau, holistique et inclusive est importante pour moi afin de répondre le plus possible aux besoins de mon homologue. Pour moi, le respect des valeurs et des attitudes des autres est une attitude de base.\n\n### Sujets\n\n* Relation\n* Partenariat\n* Modèles relationnels / conflits relationnels\n* Rester ensemble / séparation \n* Parentalité\n* Familles\n* Familles recomposées\n* Coparentalité\n* Éducation\n* Puberté\n* Monogamie / polyamour\n* Formes alternatives de relation\n* Sexualité\n* Identité / Recherche d'identité\n* Orientation sexuelle\n* LBTQI\n\nJe travaille de manière intégrative avec une attitude sexuellement positive et valorise les approches personnalisées. En accord avec ma formation et ma formation continue, la base de mon approche est une approche systémique. En plus du conseil systémique, j'intègre des méthodes issues de l'hypnosystème, de la sexothérapie ou travaille avec des techniques de constellation.\n\n### Langues\n\nJe propose mes conseils en allemand et en français.\n\n### Offre & tarifs"
    },
    {
      "title": "p2",
      "listcontent": [
        {
          "definitionlist": {
            "title": "Personnes:",
            "desc": "150.- CHF/h."
          }
        },
        {
          "definitionlist": {
            "title": "Couples:",
            "desc": "170.- CHF/h."
          }
        },
        {
          "definitionlist": {
            "title": "Multi-personnes / Familles:",
            "desc": "190.- CHF/h."
          }
        }
      ],
      "textcontent": ""
    },
    {
      "title": "p3",
      "textcontent": "Les frais ne sont pas pris en charge par l'assurance maladie. Un ajustement en fonction de votre situation financière est possible après consultation."
    }
  ]
}